bengali/__init__.py
bengali/date.py
bengali-0.0.1.dist-info/LICENSE
bengali-0.0.1.dist-info/METADATA
bengali-0.0.1.dist-info/WHEEL
bengali-0.0.1.dist-info/top_level.txt
bengali-0.0.1.dist-info/RECORD
