Metadata-Version: 2.1
Name: bengali
Version: 0.0.1
Summary: A Python package for Bengali language processing related tasks.
Home-page: https://github.com/faruk-ahmad/bengali
Author: Faruk Ahmad
Author-email: faruk.csebrur@gmail.com
License: MIT
Platform: UNKNOWN
Classifier: Programming Language :: Python :: 3
Classifier: License :: OSI Approved :: MIT License
Classifier: Operating System :: OS Independent
Requires-Python: >=3.5
